hexgenerative/__init__.py
hexgenerative/client.py
hexgenerative/models.py
hexgenerative-1.1.0.dist-info/licenses/LICENSE
hexgenerative-1.1.0.dist-info/METADATA
hexgenerative-1.1.0.dist-info/WHEEL
hexgenerative-1.1.0.dist-info/top_level.txt
hexgenerative-1.1.0.dist-info/RECORD
