Metadata-Version: 2.4
Name: hexgenerative
Version: 1.1.0
Summary: Official Python SDK for Hexa AI - Lightning-Fast AI API
Author-email: Hexa Innovate <support@shipflowstore.store>
Maintainer-email: Hexa Innovate <support@shipflowstore.store>
License: MIT
Project-URL: Homepage, https://shipflowstore.store
Project-URL: Documentation, https://docs.shipflowstore.store
Project-URL: Repository, https://github.com/hexainnovate/hexgenerative-python
Project-URL: Changelog, https://github.com/hexainnovate/hexgenerative-python/blob/main/CHANGELOG.md
Project-URL: Bug Tracker, https://github.com/hexainnovate/hexgenerative-python/issues
Keywords: ai,api,hexa,llm,chat,generative,openai,gpt,machine-learning
Classifier: Development Status :: 5 - Production/Stable
Classifier: Intended Audience :: Developers
Classifier: License :: OSI Approved :: MIT License
Classifier: Operating System :: OS Independent
Classifier: Programming Language :: Python :: 3
Classifier: Programming Language :: Python :: 3.8
Classifier: Programming Language :: Python :: 3.9
Classifier: Programming Language :: Python :: 3.10
Classifier: Programming Language :: Python :: 3.11
Classifier: Programming Language :: Python :: 3.12
Classifier: Topic :: Scientific/Engineering :: Artificial Intelligence
Classifier: Topic :: Software Development :: Libraries :: Python Modules
Requires-Python: >=3.8
License-File: LICENSE
Requires-Dist: httpx>=0.24.0
Provides-Extra: dev
Requires-Dist: pytest>=7.0.0; extra == "dev"
Requires-Dist: pytest-asyncio>=0.21.0; extra == "dev"
Dynamic: license-file
